Workbook

Sheet >> Start Here
A1: Definitions / Additional information
B2: When do we do pricing | C2: Pricing is done between April - Aug of the current year, ahead of the Sept - Dec distribution. We are guided by the current market conditions and the current year's budget which was completed in Oct of the previous year
B3: How we determine pricing | C3: In determining price of a bundle we try to balance the following considerations 1) The product margin should be between 20 - 30% 2) The price should be within +-5% of the current season market price 3) The price should be within 30% of last year's prices
B4: Adoption % | C4: The % of farmers who enrolled, paid the prepayment and received input for a specific bundle
B5: COGS | C5: Cost of Goods Sold
A7: Tabs in this workbook
B8: Pricing Model | C8: This is the main output of the deliverable. The model template is linked to the input sheet. Therefore start by updating the input sheet
B9: Input sheet | C9: Update the pricing model based on data from other tabs.
C10: You will be required to use the context provided to calculate the selling price.
B11: Bundle configuration | C11: This shows the COGS for the different bundles
B12: Site Economics | C12: Shows the YoY performance. 2024 numbers will be pulled from the Pricing Model
B13: 2023 Adoption | C13: The 2023 distribution ended in December 2023 and this report shows the final adoption for the various bundles from Roster (our famer interface application)

Sheet Pricing Model
C1: Southern Region | D1: Central Region | E1: Core Program USD
B2: Number of Regions | C2: 1 | D2: 1 | E2: =SUM(C2:D2) -> 2
B3: Number of Districts | C3: 6 | D3: 2 | E3: =SUM(C3:D3) -> 8
B4: Site Numbers | C4: 180 | D4: =65+60 -> 125 | E4: =SUM(C4:D4) -> 305
B5: Farmers per Site | C5: 489 | D5: 454.84 | E5: =E6/E4 -> 0
B6: Total Farmers
B7: Total Revenue
B8: COGS
B9: Funeral Insurance per Farmer | C9: 0 | D9: 0 | E9: =SUM(C9:D9) -> 0
B10: Inventory shrink | C10: =D10 -> 0.005 | D10: =E10 -> 0.005 | E10: 0.005
B11: Total COGS | C11: =C8-(C9/C15*C6/1000)+(C10*C8) -> 0 | D11: =D8-(D9/D15*D6/1000)+(D10*D8) -> 0 | E11: =SUM(C11:D11) -> 0
B12: Margin | C12: =sum(C7,C11) -> 0 | D12: =sum(D7,D11) -> 0 | E12: =sum(E7,E11) -> 0
B13: Margin % | C13: =C12/C7 -> #DIV/0! | D13: =D12/D7 -> #DIV/0! | E13: =E12/E7 -> #DIV/0!
B14: TX Size | C14: =C7*1000/C6 -> #DIV/0! | D14: =D7*1000/D6 -> #DIV/0! | E14: =E7*1000/E6 -> #DIV/0!
B15: FX rate | C15: =IFERROR(__xludf.DUMMYFUNCTION("importrange(""https://docs.google.com/spreadsheets/d/1c1Y7VPm6-NXUmjLXeQDgkBENw4xVCl51sk_IItPcjCY/edit#gid=748615133"",""FX Rates!b5"")"),1242.2529166666666) -> 1242.2529 | D15: =C15 -> 1242.2529 | E15: =D15 -> 1242.2529

Sheet Input Sheet
E5: Southern Region | I5: Central Region
C6: Item | E6: Adoption % | F6: Units (No. Farmers) | G6: COGS (MWK) | H6: Selling Price (MWK) | I6: Adoption % | J6: Units | K6: COGS (MWK) | L6: Selling Price (MWK) | M6: Market Prices LR25 | N6: Delta | O6: Last Year Prices | P6: Delta | Q6: Total Adoption units | R6: Total Adoption % | S6: LR24 Total Adoption | T6: Total Revenue ($) | U6: Total COGs ($) | V6: Total Margin ($) | W6: Product Margin %
C7: Maize Bundle - Standard
C8: 0.2 Acre Maize bundle | F8: =E8*'Pricing Model'!$C$6 -> 0 | J8: =I8*'Pricing Model'!$D$6 -> 0 | K8: =G8 | L8: =H8 | M8: 40000 | N8: =IFERROR($H8/M8-1, 0) -> -1 | O8: 32800 | P8: =IFERROR($H8/O8-1, 0) -> -1 | Q8: =SUM($F8,$J8) -> 0 | R8: =SUM($F8,$J8)/'Pricing Model'!$E$6 -> #DIV/0! | S8: 0.046 | W8: =IFERROR((H8-G8)/H8, 0) -> 0
C9: Maize Bundle - Reduced Urea
C10: 1.5 Acre Maize bundle | F10: =E10*'Pricing Model'!$C$6 -> 0 | J10: =I10*'Pricing Model'!$D$6 -> 0 | K10: =G10 | L10: =H10 | M10: =M11*1.5 -> 240000 | N10: =IFERROR($H10/M10-1, 0) -> -1 | O10: 201000 | P10: =IFERROR($H10/O10-1, 0) -> -1 | Q10: =SUM($F10,$J10) -> 0 | R10: =SUM($F10,$J10)/'Pricing Model'!$E$6 -> #DIV/0! | S10: 0.007 | W10: =IFERROR((H10-G10)/H10, 0) -> 0
C11: 1 Acre Maize bundle | F11: =E11*'Pricing Model'!$C$6 -> 0 | J11: =I11*'Pricing Model'!$D$6 -> 0 | K11: =G11 | L11: =H11 | M11: 160000 | N11: =IFERROR($H11/M11-1, 0) -> -1 | O11: 134000 | P11: =IFERROR($H11/O11-1, 0) -> -1 | Q11: =SUM($F11,$J11) -> 0 | R11: =SUM($F11,$J11)/'Pricing Model'!$E$6 -> #DIV/0! | S11: 0.587 | W11: =IFERROR((H11-G11)/H11, 0) -> 0
C12: 1/2 Acre Maize bundle | F12: =E12*'Pricing Model'!$C$6 -> 0 | J12: =I12*'Pricing Model'!$D$6 -> 0 | K12: =G12 | L12: =H12 | M12: =M11/2 -> 80000 | N12: =IFERROR($H12/M12-1, 0) -> -1 | O12: 67000 | P12: =IFERROR($H12/O12-1, 0) -> -1 | Q12: =SUM($F12,$J12) -> 0 | R12: =SUM($F12,$J12)/'Pricing Model'!$E$6 -> #DIV/0! | S12: 0.359 | W12: =IFERROR((H12-G12)/H12, 0) -> 0
C13: Top up Products
C14: Urea; 46-0-0; 25 KG Bag [Stock] | F14: =E14*'Pricing Model'!$C$6 -> 0 | J14: =I14*'Pricing Model'!$D$6 -> 0 | K14: =G14 | L14: =H14 | M14: 40000 | N14: =IFERROR($H14/M14-1, 0) -> -1 | O14: 32300 | P14: =IFERROR($H14/O14-1, 0) -> -1 | Q14: =SUM($F14,$J14) -> 0 | R14: =SUM($F14,$J14)/'Pricing Model'!$E$6 -> #DIV/0! | S14: 0 | W14: =IFERROR((H14-G14)/H14, 0) -> 0
C15: Urea; 46-0-0;12.5 KG Bag [Stock] | F15: =E15*'Pricing Model'!$C$6 -> 0 | J15: =I15*'Pricing Model'!$D$6 -> 0 | K15: =G15 | L15: =H15 | M15: =M14/2 -> 20000 | N15: =IFERROR($H15/M15-1, 0) -> -1 | O15: 16150 | P15: =IFERROR($H15/O15-1, 0) -> -1 | Q15: =SUM($F15,$J15) -> 0 | R15: =SUM($F15,$J15)/'Pricing Model'!$E$6 -> #DIV/0! | S15: 0 | W15: =IFERROR((H15-G15)/H15, 0) -> 0
C16: Maize Seed 10 kg | F16: =E16*'Pricing Model'!$C$6 -> 0 | J16: =I16*'Pricing Model'!$D$6 -> 0 | K16: =G16 | L16: =H16 | M16: 38000 | N16: =IFERROR($H16/M16-1, 0) -> -1 | O16: 40900 | P16: =IFERROR($H16/O16-1, 0) -> -1 | Q16: =SUM($F16,$J16) -> 0 | R16: =SUM($F16,$J16)/'Pricing Model'!$E$6 -> #DIV/0! | S16: 0 | W16: =IFERROR((H16-G16)/H16, 0) -> 0
C17: Maize Seed 5 kg | F17: =E17*'Pricing Model'!$C$6 -> 0 | J17: =I17*'Pricing Model'!$D$6 -> 0 | K17: =G17 | L17: =H17 | M17: 19000 | N17: =IFERROR($H17/M17-1, 0) -> -1 | O17: 20700 | P17: =IFERROR($H17/O17-1, 0) -> -1 | Q17: =SUM($F17,$J17) -> 0 | R17: =SUM($F17,$J17)/'Pricing Model'!$E$6 -> #DIV/0! | S17: 0 | W17: =IFERROR((H17-G17)/H17, 0) -> 0
C18: Legume; Groundnuts CG9; 2KG[Stock] | F18: =E18*'Pricing Model'!$C$6 -> 0 | J18: =I18*'Pricing Model'!$D$6 -> 0 | K18: =G18 | L18: =H18 | M18: 5000 | N18: =IFERROR($H18/M18-1, 0) -> -1 | O18: 3900 | P18: =IFERROR($H18/O18-1, 0) -> -1 | Q18: =SUM($F18,$J18) -> 0 | R18: =SUM($F18,$J18)/'Pricing Model'!$E$6 -> #DIV/0! | S18: 0.16 | W18: =IFERROR((H18-G18)/H18, 0) -> 0
C19: Legume; Groundnuts CG9; 4KG[Stock] | F19: =E19*'Pricing Model'!$C$6 -> 0 | J19: =I19*'Pricing Model'!$D$6 -> 0 | K19: =G19 | L19: =H19 | M19: 8500 | N19: =IFERROR($H19/M19-1, 0) -> -1 | O19: 7800 | P19: =IFERROR($H19/O19-1, 0) -> -1 | Q19: =SUM($F19,$J19) -> 0 | R19: =SUM($F19,$J19)/'Pricing Model'!$E$6 -> #DIV/0! | S19: 0.029 | W19: =IFERROR((H19-G19)/H19, 0) -> 0
C20: Legume; Groundnuts CG9; 10KG[Stock] | F20: =E20*'Pricing Model'!$C$6 -> 0 | J20: =I20*'Pricing Model'!$D$6 -> 0 | K20: =G20 | L20: =H20 | M20: 22500 | N20: =IFERROR($H20/M20-1, 0) -> -1 | O20: 19500 | P20: =IFERROR($H20/O20-1, 0) -> -1 | Q20: =SUM($F20,$J20) -> 0 | R20: =SUM($F20,$J20)/'Pricing Model'!$E$6 -> #DIV/0! | S20: 0.03 | W20: =IFERROR((H20-G20)/H20, 0) -> 0
C21: Legume; Groundnuts CG9; 20KG[Stock] | F21: =E21*'Pricing Model'!$C$6 -> 0 | J21: =I21*'Pricing Model'!$D$6 -> 0 | K21: =G21 | L21: =H21 | M21: 42000 | N21: =IFERROR($H21/M21-1, 0) -> -1 | O21: 39000 | P21: =IFERROR($H21/O21-1, 0) -> -1 | Q21: =SUM($F21,$J21) -> 0 | R21: =SUM($F21,$J21)/'Pricing Model'!$E$6 -> #DIV/0! | S21: 0.002 | W21: =IFERROR((H21-G21)/H21, 0) -> 0
C22: Legume; Groundnut CG13; 1 KG [Stock] | F22: =E22*'Pricing Model'!$C$6 -> 0 | J22: =I22*'Pricing Model'!$D$6 -> 0 | K22: =G22 | L22: =H22 | M22: 5000 | N22: =IFERROR($H22/M22-1, 0) -> -1 | O22: 3900 | P22: =IFERROR($H22/O22-1, 0) -> -1 | Q22: =SUM($F22,$J22) -> 0 | R22: =SUM($F22,$J22)/'Pricing Model'!$E$6 -> #DIV/0! | S22: 0.136 | W22: =IFERROR((H22-G22)/H22, 0) -> 0
C23: Legume; Groundnut CG13; 2 KG [Stock] | F23: =E23*'Pricing Model'!$C$6 -> 0 | J23: =I23*'Pricing Model'!$D$6 -> 0 | K23: =G23 | L23: =H23 | M23: 8500 | N23: =IFERROR($H23/M23-1, 0) -> -1 | O23: 7800 | P23: =IFERROR($H23/O23-1, 0) -> -1 | Q23: =SUM($F23,$J23) -> 0 | R23: =SUM($F23,$J23)/'Pricing Model'!$E$6 -> #DIV/0! | S23: 0.023 | W23: =IFERROR((H23-G23)/H23, 0) -> 0
C24: Legume; Groundnut CG13; 5 KG [Stock] | F24: =E24*'Pricing Model'!$C$6 -> 0 | J24: =I24*'Pricing Model'!$D$6 -> 0 | K24: =G24 | L24: =H24 | M24: 22500 | N24: =IFERROR($H24/M24-1, 0) -> -1 | O24: 19500 | P24: =IFERROR($H24/O24-1, 0) -> -1 | Q24: =SUM($F24,$J24) -> 0 | R24: =SUM($F24,$J24)/'Pricing Model'!$E$6 -> #DIV/0! | S24: 0.026 | W24: =IFERROR((H24-G24)/H24, 0) -> 0
C25: Legume; Groundnut CG13; 10 KG [Stock] | F25: =E25*'Pricing Model'!$C$6 -> 0 | J25: =I25*'Pricing Model'!$D$6 -> 0 | K25: =G25 | L25: =H25 | M25: 42000 | N25: =IFERROR($H25/M25-1, 0) -> -1 | O25: 39000 | P25: =IFERROR($H25/O25-1, 0) -> -1 | Q25: =SUM($F25,$J25) -> 0 | R25: =SUM($F25,$J25)/'Pricing Model'!$E$6 -> #DIV/0! | S25: 0 | W25: =IFERROR((H25-G25)/H25, 0) -> 0
C26: Legume; Groundnut CG13; 20 KG [Stock] | F26: =E26*'Pricing Model'!$C$6 -> 0 | J26: =I26*'Pricing Model'!$D$6 -> 0 | K26: =G26 | L26: =H26 | M26: 84000 | N26: =IFERROR($H26/M26-1, 0) -> -1 | O26: 78000 | P26: =IFERROR($H26/O26-1, 0) -> -1 | Q26: =SUM($F26,$J26) -> 0 | R26: =SUM($F26,$J26)/'Pricing Model'!$E$6 -> #DIV/0! | S26: 0 | W26: =IFERROR((H26-G26)/H26, 0) -> 0
C27: Legume; Nua-45 beans; 1KG[Stock] | F27: =E27*'Pricing Model'!$C$6 -> 0 | J27: =I27*'Pricing Model'!$D$6 -> 0 | K27: =G27 | L27: =H27 | M27: 3800 | N27: =IFERROR($H27/M27-1, 0) -> -1 | O27: 4300 | P27: =IFERROR($H27/O27-1, 0) -> -1 | Q27: =SUM($F27,$J27) -> 0 | R27: =SUM($F27,$J27)/'Pricing Model'!$E$6 -> #DIV/0! | S27: 0.161 | W27: =IFERROR((H27-G27)/H27, 0) -> 0
... C46: Legume; Soya Beans SC Serenade 20KG[Stock] | F46: =E46*'Pricing Model'!$C$6 -> 0 | J46: =I46*'Pricing Model'!$D$6 -> 0 | K46: =G46 | L46: =H46 | M46: 60000 | N46: =IFERROR($H46/M46-1, 0) -> -1 | O46: 66000 | P46: =IFERROR($H46/O46-1, 0) -> -1 | Q46: =SUM($F46,$J46) -> 0 | R46: =SUM($F46,$J46)/'Pricing Model'!$E$6 -> #DIV/0! | S46: 0 | W46: =IFERROR((H46-G46)/H46, 0) -> 0
C47: Legume; Cow Peas (IT82E-16);1Kg | F47: 0 | J47: =I47*'Pricing Model'!$D$6 -> 0 | K47: =G47 | L47: =H47 | M47: 3000 | N47: =IFERROR($H47/M47-1, 0) -> -1 | O47: 2800 | P47: =IFERROR($H47/O47-1, 0) -> -1 | Q47: =SUM($F47,$J47) -> 0 | R47: =SUM($F47,$J47)/'Pricing Model'!$E$6 -> #DIV/0! | S47: 0.054 | W47: =IFERROR((H47-G47)/H47, 0) -> 0
C48: Legume; Cow Peas (IT82E-16);2Kg | F48: 0 | J48: =I48*'Pricing Model'!$D$6 -> 0 | K48: =G48 | L48: =H48 | M48: 6000 | N48: =IFERROR($H48/M48-1, 0) -> -1 | O48: 5600 | P48: =IFERROR($H48/O48-1, 0) -> -1 | Q48: =SUM($F48,$J48) -> 0 | R48: =SUM($F48,$J48)/'Pricing Model'!$E$6 -> #DIV/0! | S48: 0.005 | W48: =IFERROR((H48-G48)/H48, 0) -> 0
C49: Legume; Cow Peas (IT82E-16);5Kg | F49: 0 | J49: =I49*'Pricing Model'!$D$6 -> 0 | K49: =G49 | L49: =H49 | M49: 15000 | N49: =IFERROR($H49/M49-1, 0) -> -1 | O49: 14000 | P49: =IFERROR($H49/O49-1, 0) -> -1 | Q49: =SUM($F49,$J49) -> 0 | R49: =SUM($F49,$J49)/'Pricing Model'!$E$6 -> #DIV/0! | S49: 0.001 | W49: =IFERROR((H49-G49)/H49, 0) -> 0
C50: Fertilizer ; Beans innoculant; 25g [Stock] | F50: =E50*'Pricing Model'!$C$6 -> 0 | J50: =I50*'Pricing Model'!$D$6 -> 0 | K50: =G50 | L50: =H50 | M50: 800 | N50: =IFERROR($H50/M50-1, 0) -> -1 | O50: 1200 | P50: =IFERROR($H50/O50-1, 0) -> -1 | Q50: =SUM($F50,$J50) -> 0 | R50: =SUM($F50,$J50)/'Pricing Model'!$E$6 -> #DIV/0! | S50: 0.013 | W50: =IFERROR((H50-G50)/H50, 0) -> 0
C51: Fertilizer; Groundnut Innoculant; 25g [Stock] | F51: =E51*'Pricing Model'!$C$6 -> 0 | J51: =I51*'Pricing Model'!$D$6 -> 0 | K51: =G51 | L51: =H51 | M51: 1000 | N51: =IFERROR($H51/M51-1, 0) -> -1 | O51: 1200 | P51: =IFERROR($H51/O51-1, 0) -> -1 | Q51: =SUM($F51,$J51) -> 0 | R51: =SUM($F51,$J51)/'Pricing Model'!$E$6 -> #DIV/0! | S51: 0.015 | W51: =IFERROR((H51-G51)/H51, 0) -> 0
C52: Fertilizer ; Soybean innoculant; 25g [Stock] | F52: =E52*'Pricing Model'!$C$6 -> 0 | J52: =I52*'Pricing Model'!$D$6 -> 0 | K52: =G52 | L52: =H52 | M52: 1100 | N52: =IFERROR($H52/M52-1, 0) -> -1 | O52: 1200 | P52: =IFERROR($H52/O52-1, 0) -> -1 | Q52: =SUM($F52,$J52) -> 0 | R52: =SUM($F52,$J52)/'Pricing Model'!$E$6 -> #DIV/0! | S52: 0.017 | W52: =IFERROR((H52-G52)/H52, 0) -> 0
C53: Planting scoop | F53: =E53*'Pricing Model'!$C$6 -> 0 | J53: =I53*'Pricing Model'!$D$6 -> 0 | K53: =G53 | L53: =H53 | M53: 100 | N53: =IFERROR($H53/M53-1, 0) -> -1 | O53: 0 | P53: =IFERROR($H53/O53-1, 0) -> 0 | Q53: =SUM($F53,$J53) -> 0 | R53: =SUM($F53,$J53)/'Pricing Model'!$E$6 -> #DIV/0! | S53: 0 | W53: =IFERROR((H53-G53)/H53, 0) -> 0
C54: Trees | F54: =E54*'Pricing Model'!$C$6 -> 0 | J54: =I54*'Pricing Model'!$D$6 -> 0 | K54: =G54 | L54: =H54 | M54: 150 | N54: =IFERROR($H54/M54-1, 0) -> -1 | O54: 0 | P54: =IFERROR($H54/O54-1, 0) -> 0 | Q54: =SUM($F54,$J54) -> 0 | R54: =SUM($F54,$J54)/'Pricing Model'!$E$6 -> #DIV/0! | S54: 0.345 | W54: =IFERROR((H54-G54)/H54, 0) -> 0
C55: Itel Phone | F55: =E55*'Pricing Model'!$C$6 -> 0 | J55: =I55*'Pricing Model'!$D$6 -> 0 | K55: =G55 | L55: =H55 | M55: 28000 | N55: =IFERROR($H55/M55-1, 0) -> -1 | O55: 24000 | P55: =IFERROR($H55/O55-1, 0) -> -1 | Q55: =SUM($F55,$J55) -> 0 | R55: =SUM($F55,$J55)/'Pricing Model'!$E$6 -> #DIV/0! | S55: 0.078 | W55: =IFERROR((H55-G55)/H55, 0) -> 0
C56: Sunking Boom | F56: =E56*'Pricing Model'!$C$6 -> 0 | J56: =I56*'Pricing Model'!$D$6 -> 0 | K56: =G56 | L56: =H56 | M56: 75000 | N56: =IFERROR($H56/M56-1, 0) -> -1 | O56: 55000 | P56: =IFERROR($H56/O56-1, 0) -> -1 | Q56: =SUM($F56,$J56) -> 0 | R56: =SUM($F56,$J56)/'Pricing Model'!$E$6 -> #DIV/0! | S56: 0.062 | W56: =IFERROR((H56-G56)/H56, 0) -> 0

Sheet Bundle Configuration
C1: DO NOT SORT OR FILTER!
C2: Bundle Name | D2: Item | E2: Product Type | F2: Number of items in bundle | G2: Quantity needed in bundle (Kg)/units | H2: COGS per bundle (MWK) - Actual | I2: COGS per bundle (USD) - Actual
C3: Standard Bundles
C4: 0.2 Acre Maize bundle | D4: NPK-23-10-5+6S+1.0Zn; 10 KG Bag [Stock] | E4: Fertilizer | F4: 1 | G4: 10 | H4: 12310.077 | I4: 9.9094772
C5: 0.2 Acre Maize bundle | D5: UREA; 46-0-0; 10 KG Bag [Stock] | E5: Fertilizer | F5: 1 | G5: 10 | H5: 7213.6025 | I5: 5.8068711
C6: 0.2 Acre Maize bundle | D6: Maize Seed 2 kg | E6: Seed | F6: 1 | G6: 2 | H6: 4628.4 | I6: 3.7258113
C7: Reduced Urea Bundles
C8: 1.5 Acre Maize bundle | D8: NPK-23-10-5+6S+1.0Zn; 50 KG Bag [Stock] | E8: Fertilizer | F8: 1 | G8: 50 | H8: 61550.385 | I8: 49.547386
C9: 1.5 Acre Maize bundle | D9: Urea; 46-0-0; 25 KG Bag [Stock] | E9: Fertilizer | F9: 1 | G9: 25 | H9: 18034.006 | I9: 14.517178
C10: 1.5 Acre Maize bundle | D10: NPK-23-10-5+6S+1.0Zn; 25 KG Bag [Stock] | E10: Fertilizer | F10: 1 | G10: 25 | H10: 30775.192 | I10: 24.773693
C11: 1.5 Acre Maize bundle | D11: Urea; 46-0-0; 25 KG Bag [Stock] | E11: Fertilizer | F11: 1 | G11: 12.5 | H11: 9017.0032 | I11: 7.2585888
C12: 1.5 Acre Maize bundle | D12: Maize Seed 10 kg | E12: Seed | F12: 1 | G12: 10 | H12: 27794.286 | I12: 22.374096
C13: 1.5 Acre Maize bundle | D13: Maize Seed 5 kg | E13: Seed | F13: 5 | G13: 5 | H13: 14031.042 | I13: 11.294835
C14: 1 Acre Maize bundle | D14: NPK-23-10-5+6S+1.0Zn; 50 KG Bag [Stock] | E14: Fertilizer | F14: 1 | G14: 50 | H14: 61550.385 | I14: 49.547386
C15: 1 Acre Maize bundle | D15: Urea; 46-0-0; 25 KG Bag [Stock] | E15: Fertilizer | F15: 1 | G15: 25 | H15: 18034.006 | I15: 14.517178
C16: 1 Acre Maize bundle | D16: Maize Seed 10 kg | E16: Seed | F16: 1 | G16: 10 | H16: 27794.286 | I16: 22.374096
C17: 1/2 Acre Maize bundle | D17: NPK-23-10-5+6S+1.0Zn; 25 KG Bag [Stock] | E17: Fertilizer | F17: 1 | G17: 25 | H17: 30775.192 | I17: 24.773693
C18: 1/2 Acre Maize bundle | D18: Urea; 46-0-0; 25 KG Bag [Stock] | E18: Fertilizer | F18: 1 | G18: 12.5 | H18: 9017.0032 | I18: 7.2585888
C19: 1/2 Acre Maize bundle | D19: Maize Seed 5 kg | E19: Seed | F19: 5 | G19: 5 | H19: 14031.042 | I19: 11.294835
... C85: Fertilizer ; Soybean innoculant; 25g [Stock] | D85: Fertilizer ; Soybean innoculant; 25g [Stock] | E85: Fertilizer | F85: 1 | G85: 25 | H85: 910.16455 | I85: 0.7326725

Sheet Site Economics
B3: 1) Site economics
B5: Site Economics | C5: 2023 - Actuals | D5: 2024 - Budget
B6: Farmer Revenue | C6: 105.68 | D6: ='Pricing Model'!E14 -> #DIV/0!
B7: Margin % | C7: 0.293 | D7: ='Pricing Model'!E13 -> #DIV/0!
B8: Gross Margin / Farmer | C8: =C7*C6 -> 30.96424 | D8: =D7*D6 -> #DIV/0!
B9: Non-repayment (% of revenue) | C9: -0.0388 | D9: -0.0412
B10: Other Associated Costs (% of revenue) | C10: -0.077 | D10: -0.1036
B11: Associated Costs (% of revenue) | C11: =sum(C9:C10) -> -0.1158 | D11: =sum(D9:D10) -> -0.1448
B12: Ass Costs / Farmer | C12: =C11*C6 -> -12.237744 | D12: =D11*D6 -> #DIV/0!
B13: $ Earned (Profit margin) / Farmer | C13: =C8+C12 -> 18.726496 | D13: =D8+D12 -> #DIV/0!
B14: Farmers / Site | C14: 418.786 | D14: ='Pricing Model'!E5 -> 0
B15: $ Margin / Site | C15: =C14*C13 -> 7842.3944 | D15: =D14*D13 -> #DIV/0!
B16: Field Staff Cost / Site | C16: -2953 | D16: -3320
B17: FOP OH Cost / Site | C17: -1805 | D17: -2126
B18: $ Costs/ Site | C18: =C16+C17 -> -4758 | D18: =D16+D17 -> -5446
B19: $ Earned / Margin Per Site | C19: =C14*C13+C18 -> 3084.3944 | D19: =D14*D13+D18 -> #DIV/0!
B20: Site #s | C20: 229 | D20: ='Pricing Model'!E4 -> 305
B21: Total Site Margin / Deficit | C21: =C20*C19 -> 706326.31 | D21: =D20*D19 -> #DIV/0!
B23: * - associated costs + staff & OH costs based on what was budgeted
B24: ** - associated costs + staff & OH costs based on actual costs from LR23

Sheet 2023 Adoption
B1: Farmer #s | C1: 26505 | D1: 82849 | E1: =SUM(C1:D1) -> 109354
B2: Bundle | C2: Central Region Adoption | D2: Malawi Southern Adoption | E2: Total Adoption
B3: 0.2 Acre Maize bundle | C3: 0 | D3: 4645 | E3: =SUM(C3:D3) -> 4645
B4: Legume; Kayera beans; 1KG[Stock] | C4: 0 | D4: 1216 | E4: =SUM(C4:D4) -> 1216
B5: Legume; Kayera beans; 2KG[Stock] | C5: 0 | D5: 165 | E5: =SUM(C5:D5) -> 165
B6: Legume; Kayera beans; 5KG[Stock] | C6: 1213 | D6: 7 | E6: =SUM(C6:D6) -> 1220
B7: Legume; Kayera beans; 10KG[Stock] | C7: 23 | D7: 0 | E7: =SUM(C7:D7) -> 23
B8: Legume; Kayera beans; 20 KG [Stock] | C8: 0 | D8: 0 | E8: =SUM(C8:D8) -> 0
B9: Legume; Nua-45 beans; 1KG[Stock] | C9: 0 | D9: 17325 | E9: =SUM(C9:D9) -> 17325
B10: Legume; Nua-45 beans; 2KG[Stock] | C10: 0 | D10: 2589 | E10: =SUM(C10:D10) -> 2589
B11: Legume; Nua-45 beans; 5KG[Stock] | C11: 7698 | D11: 237 | E11: =SUM(C11:D11) -> 7935
B12: Legume; Nua-45 beans; 10KG[Stock] | C12: 180 | D12: 5 | E12: =SUM(C12:D12) -> 185
B13: Legume; Nua-45 beans; 20KG[Stock] | C13: 2 | D13: 0 | E13: =SUM(C13:D13) -> 2
B14: Legume; Cow Peas (IT82E-16);1Kg | C14: 0 | D14: 9247 | E14: =SUM(C14:D14) -> 9247
... B48: Urea; 46-0-0;12.5 KG Bag [Stock] | C48: 0 | D48: 0 | E48: =SUM(C48:D48) -> 0
